{
  "section": "11i02",
  "chapter": "11",
  "section_title": "11i02 - Insecticide,\nchemical and fertilizer producers.",
  "text": "Employees of an\nestablishment which produces insecticides, chemicals or fertilizers for\nagricultural used solely within the State are not engaged in interstate\ncommerce or in the production of goods for interstate commerce. Some concerns\nsell and actually apply insecticides, chemicals or fertilizers on farms\nproducing goods for interstate commerce. The employees of such concerns who handle,\nload, maintain records, etc., of such activities are individually covered by\nthe Act.",
  "html": "<p>Employees of an\nestablishment which produces insecticides, chemicals or fertilizers for\nagricultural used solely within the State are not engaged in interstate\ncommerce or in the production of goods for interstate commerce. Some concerns\nsell and actually apply insecticides, chemicals or fertilizers on farms\nproducing goods for interstate commerce. The employees of such concerns who handle,\nload, maintain records, etc., of such activities are individually covered by\nthe Act.</p>"
}