{
  "chapter": "Chapter 39 - THE FAMILY AND MEDICAL LEAVE ACT (FMLA)",
  "results": [
    {
      "sections": []
    },
    {
      "subchapter": "39a - GENERAL",
      "sections": [
        "39a00 - Statutory and regulatory provisions.",
        "39a01 - Geographical scope.",
        "39a02 - FMLA protections.",
        "39a03 - Waiver of rights."
      ]
    },
    {
      "subchapter": "39b - EMPLOYER COVERAGE",
      "sections": [
        "39b00 - General.",
        "39b01 - Joint employment.",
        "39b02 - Successor in interest.",
        "39b03 - Public agencies, general.",
        "39b04 - Public agencies, federal government.",
        "39b05 - Schools.",
        "39b06 - Members of the military."
      ]
    },
    {
      "subchapter": "39c - EMPLOYEE ELIGIBILITY",
      "sections": [
        "39c00 - General.",
        "39c01 - 12 months of service.",
        "39c02 - Hours of service, general.",
        "39c03 - Employees within 75 miles.",
        "39c04 - Temporary employees jointly employed."
      ]
    },
    {
      "subchapter": "39d - REASONS FOR LEAVE",
      "sections": [
        "39d00 - Qualifying reasons for FMLA leave.",
        "39d01 - Leave for birth or pregnancy.",
        "39d02 - Leave for placement of a child for adoption or foster care.",
        "39d03 - Leave to care for spouse, son, daughter, or parent with a serious health condition.",
        "39d04 - Employee’s own serious health condition.",
        "39d05 - Documentation of relationship.",
        "39d06 - Serious health condition.",
        "39d07 - Treatment for substance abuse.",
        "39d08 - Qualifying exigency leave.",
        "39d09 - Military caregiver leave."
      ]
    },
    {
      "subchapter": "39e - COUNTING FMLA LEAVE USAGE",
      "sections": [
        "39e00 - FMLA leave entitlement.",
        "39e01 - Intermittent leave.",
        "39e02 - Substitution of accrued paid leave.",
        "39e03 - Spouses employed by same employer.",
        "39e04 - Effects on an employee’s salary."
      ]
    },
    {
      "subchapter": "39f - EMPLOYEE NOTICE REQUIREMENTS",
      "sections": [
        "39f00 - General.",
        "39f01 - Notice of foreseeable leave.",
        "39f02 - Notice of unforeseeable leave.",
        "39f03 -            Failure to comply with FMLA notification policies."
      ]
    },
    {
      "subchapter": "39g - EMPLOYER NOTICE REQUIREMENTS",
      "sections": [
        "39g00 - Required notices.",
        "39g01 - Designation of FMLA leave."
      ]
    },
    {
      "subchapter": "39h - CERTIFICATION AND DOCUMENTATION",
      "sections": [
        "39h00 - General.",
        "39h01 - Medical certification of a serious health condition.",
        "39h02 - Fitness-for-duty certification.",
        "39h03 - Employee failure to provide certification.",
        "39h04 - Health care provider.",
        "39h05 -           Documentation of relationship.",
        "39h06 - Certification for qualifying exigency leave.",
        "39h07 - Certification for military caregiver leave."
      ]
    },
    {
      "subchapter": "39i - MAINTENANCE OF EMPLOYEE BENEFITS",
      "sections": [
        "39i00 - Maintaining group health plan benefits.",
        "39i01 - Maintaining non-health benefits.",
        "39i02 - Employee choice to not retain group health benefits.",
        "39i03 - Payment of group health plan premiums.",
        "39i04 - Maintenance of benefits under multi-employer health plans.",
        "39i05 - Valid reasons for ending employee group health plan coverage.",
        "39i06 - Employee failure to pay premiums.",
        "39i07 - Employer recovery of benefit costs."
      ]
    },
    {
      "subchapter": "39j - JOB RESTORATION",
      "sections": [
        "39j00 - General.",
        "39j01 -            Equivalent position.",
        "39j02 -            Equivalent pay.",
        "39j03 - Equivalent benefits.",
        "39j04 - Equivalent terms and conditions of employment.",
        "39j05 - De minimis exception.",
        "39j06 - Limitations to employee reinstatement.",
        "39j07 - “Light duty” job offer."
      ]
    },
    {
      "subchapter": "39k - RECORDKEEPING REQUIREMENTS",
      "sections": [
        "39k00 - General.",
        "39k01 - Content of records.",
        "39k02 - Covered employers with no FMLA-eligible employees.",
        "39k03 - Confidentiality of records."
      ]
    },
    {
      "subchapter": "39L - SPECIAL RULES FOR SCHOOLS",
      "sections": [
        "39L00 - General.",
        "39L01 - Limitations on intermittent leave.",
        "39L02 - Limitations on leave taken near the end of an academic term.",
        "39L03 - Restoration to an equivalent position."
      ]
    },
    {
      "subchapter": "39m - SPECIAL RULES FOR AIRLINE FLIGHT CREW EMPLOYEES",
      "sections": [
        "39m00 - General.",
        "39m01 - Eligibility – hours of service requirement.",
        "39m02 - Calculation of leave.",
        "39m03 - Special recordkeeping requirements."
      ]
    },
    {
      "subchapter": "39n - INTERACTION WITH FEDERAL OR STATE LAWS",
      "sections": [
        "39n00 - State family and medical leave laws.",
        "39n01 - Federal and state anti-discrimination laws.",
        "39n02 - Worker’s compensation.",
        "39n03 - Consolidated Omnibus Budget Reconciliation Act (COBRA).",
        "39n04 - Uniformed Services Employment and Reemployment Rights Act (USERRA).",
        "39n05 - Health Insurance Portability and Accountability Act (HIPAA) Privacy Rule."
      ]
    },
    {
      "subchapter": "39o - ADVERSE ACTIONS AND ENFORCEMENT",
      "sections": [
        "39o00 - Interference with the right to take FMLA leave.",
        "39o01 - Interference with proceedings or inquiries.",
        "39o02 - Enforcement."
      ]
    }
  ]
}