{
  "section": "12g13",
  "chapter": "12",
  "title": "12g13  - Driving schools.",
  "text": "Establishments engaged as a business in instructing and teaching motor\nvehicle driving are not bona fide educational establishments or institutions\nfor purposes of Sec 3(s)(5) or Reg 541.215.",
  "html": "<p> </p><p>Establishments engaged as a business in instructing and teaching motor\nvehicle driving are not bona fide educational establishments or institutions\nfor purposes of Sec 3(s)(5) or Reg 541.215.</p><p> </p>"
}